discord_virtual_micro/__init__.py
discord_virtual_micro/__main__.py
discord_virtual_micro/client.py
discord_virtual_micro/config-example.json
discord_virtual_micro/speach.py
discord_virtual_micro/abc/command.py
discord_virtual_micro/abc/event.py
discord_virtual_micro/commands/del_word.py
discord_virtual_micro/commands/set_word.py
discord_virtual_micro/events/on_command_error.py
discord_virtual_micro/events/on_message.py
discord_virtual_micro/events/on_ready.py
discord_virtual_micro/patches/get_signature_parameters.py
discord_virtual_micro/utils/config.py
discord_virtual_micro/utils/module.py
discord_virtual_micro/utils/patcher.py
discord_virtual_micro/utils/text.py
discord_virtual_micro-0.1.2.dist-info/METADATA
discord_virtual_micro-0.1.2.dist-info/WHEEL
discord_virtual_micro-0.1.2.dist-info/entry_points.txt
discord_virtual_micro-0.1.2.dist-info/licenses/LICENSE
discord_virtual_micro-0.1.2.dist-info/RECORD
