Metadata-Version: 2.4
Name: discord-virtual-micro
Version: 0.1.2
Summary: Discord Virtual Microphone is a bot that leverages AI from Silero Models to read out loud any text you type in Discord. This bot can be particularly useful for individuals without access to a physical microphone.
Project-URL: Homepage, https://github.com/Vazgen005/discord-virtual-micro
Project-URL: Issues, https://github.com/Vazgen005/discord-virtual-micro/issues
Author-email: Vazgen <norvardyanvazgen@gmail.com>
License-File: LICENSE
Requires-Python: <3.13,>=3.10
Requires-Dist: aiorun
Requires-Dist: discord-py-self
Requires-Dist: librosa
Requires-Dist: llvmlite==0.43.0
Requires-Dist: num2words
Requires-Dist: setuptools
Requires-Dist: silero
Requires-Dist: soundcard
Requires-Dist: transliterate
